video_encoding/__init__.py
video_encoding/admin.py
video_encoding/backends/__init__.py
video_encoding/backends/base.py
video_encoding/backends/ffmpeg.py
video_encoding/compat.py
video_encoding/config.py
video_encoding/exceptions.py
video_encoding/fields.py
video_encoding/files.py
video_encoding/manager.py
video_encoding/migrations/0001_initial.py
video_encoding/migrations/0002_update_field_definitions.py
video_encoding/migrations/__init__.py
video_encoding/models.py
video_encoding/tasks.py
django_video_encoding-0.4.0.dist-info/LICENSE
django_video_encoding-0.4.0.dist-info/WHEEL
django_video_encoding-0.4.0.dist-info/METADATA
django_video_encoding-0.4.0.dist-info/RECORD
