Metadata-Version: 2.1
Name: django-video-encoding
Version: 0.4.0
Summary: django-video-encoding helps to convert your videos into different formats and resolutions.
Home-page: https://github.com/escaped/django-video-encoding
License: BSD-3-Clause
Author: Alexander Frenzel
Author-email: alex@relatedworks.com
Requires-Python: >=2.7, !=3.0.*, !=3.1.*, !=3.2.*, !=3.3.*, !=3.4.*
Classifier: Development Status :: 4 - Beta
Classifier: Environment :: Web Environment
Classifier: Framework :: Django
Classifier: Intended Audience :: Developers
Classifier: License :: OSI Approved :: BSD License
Classifier: Operating System :: OS Independent
Classifier: Programming Language :: Python
Classifier: Programming Language :: Python :: 2
Classifier: Programming Language :: Python :: 2.7
Classifier: Programming Language :: Python :: 3
Classifier: Programming Language :: Python :: 3.5
Classifier: Programming Language :: Python :: 3.6
Classifier: Programming Language :: Python :: 3.7
Classifier: Topic :: Software Development :: Libraries :: Python Modules
Requires-Dist: django-appconf (>=1.0,<2.0)
Requires-Dist: pillow (>=5.0,<6.0)
Requires-Dist: shutilwhich (>=1.1,<2.0)
Requires-Dist: six (>=1.6,<2.0)
Project-URL: Documentation, https://github.com/escaped/django-video-encoding/blob/master/README.rst
Project-URL: Repository, https://github.com/escaped/django-video-encoding
